pyside2_vfx_template/__init__.py
pyside2_vfx_template/actions.py
pyside2_vfx_template/dcc.py
pyside2_vfx_template/example.py
pyside2_vfx_template/shadows.py
pyside2_vfx_template/splashscreen.py
pyside2_vfx_template/style.jsonc
pyside2_vfx_template/style.py
pyside2_vfx_template/tree_widget.py
pyside2_vfx_template/utils.py
pyside2_vfx_template/window.py
pyside2_vfx_template/__pycache__/actions.cpython-39.pyc
pyside2_vfx_template/__pycache__/shadows.cpython-39.pyc
pyside2_vfx_template/__pycache__/splashscreen.cpython-39.pyc
pyside2_vfx_template/__pycache__/style.cpython-39.pyc
pyside2_vfx_template/__pycache__/utils.cpython-39.pyc
pyside2_vfx_template/__pycache__/window.cpython-39.pyc
pyside2_vfx_template/icons/Hmovetoolbar_dark.png
pyside2_vfx_template/icons/Hmovetoolbar_light.png
pyside2_vfx_template/icons/Hsepartoolbar_dark.png
pyside2_vfx_template/icons/Hsepartoolbar_light.png
pyside2_vfx_template/icons/Vmovetoolbar_dark.png
pyside2_vfx_template/icons/Vmovetoolbar_light.png
pyside2_vfx_template/icons/Vsepartoolbar_dark.png
pyside2_vfx_template/icons/Vsepartoolbar_light.png
pyside2_vfx_template/icons/branch_closed-on.png
pyside2_vfx_template/icons/branch_closed.png
pyside2_vfx_template/icons/branch_closed_dark.png
pyside2_vfx_template/icons/branch_closed_darker.png
pyside2_vfx_template/icons/branch_end.png
pyside2_vfx_template/icons/branch_more.png
pyside2_vfx_template/icons/branch_open-on.png
pyside2_vfx_template/icons/branch_open.png
pyside2_vfx_template/icons/branch_open_dark.png
pyside2_vfx_template/icons/branch_open_darker.png
pyside2_vfx_template/icons/branch_vline.png
pyside2_vfx_template/icons/checkbox_dark.png
pyside2_vfx_template/icons/checkbox_indeterminate_dark.png
pyside2_vfx_template/icons/checkbox_indeterminate_light.png
pyside2_vfx_template/icons/checkbox_light.png
pyside2_vfx_template/icons/close_dark.png
pyside2_vfx_template/icons/close_light.png
pyside2_vfx_template/icons/down_arrow_dark.png
pyside2_vfx_template/icons/down_arrow_darker.png
pyside2_vfx_template-1.1.0.dist-info/LICENSE
pyside2_vfx_template-1.1.0.dist-info/METADATA
pyside2_vfx_template-1.1.0.dist-info/WHEEL
pyside2_vfx_template-1.1.0.dist-info/top_level.txt
pyside2_vfx_template-1.1.0.dist-info/RECORD
