Metadata-Version: 2.1
Name: pyside2-vfx-template
Version: 1.1.0
Summary: Custom Python classes and utilities tailored for PySide2 built UI, in VFX-oriented DCC applications.
Home-page: UNKNOWN
Author: Valentin Beaumont
Author-email: valentin.onze@gmail.com
License: UNKNOWN
Platform: UNKNOWN
License-File: LICENSE
Requires-Dist: PySide2
Requires-Dist: qdarkstyle
